mseep_mcp_code_checker-0.1.0.dist-info/licenses/LICENSE
src/__init__.py
src/code_checker_pylint.py
src/main.py
src/server.py
src/code_checker_pytest/__init__.py
src/code_checker_pytest/models.py
src/code_checker_pytest/parsers.py
src/code_checker_pytest/reporting.py
src/code_checker_pytest/runners.py
src/code_checker_pytest/utils.py
tests/__init__.py
tests/test_code_checker_pylint.py
tests/test_server_params.py
mseep_mcp_code_checker-0.1.0.dist-info/METADATA
mseep_mcp_code_checker-0.1.0.dist-info/WHEEL
mseep_mcp_code_checker-0.1.0.dist-info/top_level.txt
mseep_mcp_code_checker-0.1.0.dist-info/RECORD
