Metadata-Version: 2.4
Name: mseep-mcp-code-checker
Version: 0.1.0
Summary: An MCP server for running code checks (pylint and pytest)
Home-page: https://github.com/mseep
Author: mseep
Author-email: support@skydeck.ai
Maintainer: mseep
Maintainer-email: support@skydeck.ai
Keywords: mseep,mcp,server,code-checker,pylint,pytest,claude,ai,assistant
Classifier: Programming Language :: Python :: 3
Classifier: License :: OSI Approved :: MIT License
Classifier: Operating System :: OS Independent
Requires-Python: >=3.6
License-File: LICENSE
Requires-Dist: pathspec>=0.12.1
Requires-Dist: mcp>=1.3.0
Requires-Dist: mcp[server]>=1.3.0
Requires-Dist: mcp[cli]>=1.3.0
Requires-Dist: pylint>=3.3.3
Requires-Dist: pytest>=8.3.5
Requires-Dist: pytest-json-report>=1.5.0
Requires-Dist: pytest-asyncio>=0.25.3
Requires-Dist: mypy>=1.9.0
Dynamic: author
Dynamic: author-email
Dynamic: classifier
Dynamic: description
Dynamic: description-content-type
Dynamic: home-page
Dynamic: keywords
Dynamic: license-file
Dynamic: maintainer
Dynamic: maintainer-email
Dynamic: requires-dist
Dynamic: requires-python
Dynamic: summary
